learning_toolbox/__init__.py
learning_toolbox/content_generator.py
learning_toolbox/file_handler.py
learning_toolbox/utils.py
learning_toolbox/wkhtmltopdf/bin/wkhtmltoimage.exe
learning_toolbox/wkhtmltopdf/bin/wkhtmltopdf.exe
learning_toolbox/wkhtmltopdf/bin/wkhtmltox.dll
learning_toolbox-0.2.0.dist-info/METADATA
learning_toolbox-0.2.0.dist-info/WHEEL
learning_toolbox-0.2.0.dist-info/top_level.txt
learning_toolbox-0.2.0.dist-info/RECORD
