Metadata-Version: 2.1
Name: learning-toolbox
Version: 0.2.0
Summary: A Python library for generating learning resources using Gemini AI and other tools.
Home-page: https://github.com/Avinash1286/learning_toolbox
Author: Abinash Yadav
Author-email: abinashyadavedu@gmail.com
License: MIT
Classifier: Development Status :: 3 - Alpha
Classifier: Intended Audience :: Developers
Classifier: Topic :: Education
Classifier: License :: OSI Approved :: MIT License
Classifier: Programming Language :: Python :: 3
Classifier: Programming Language :: Python :: 3.6
Classifier: Programming Language :: Python :: 3.7
Classifier: Programming Language :: Python :: 3.8
Classifier: Programming Language :: Python :: 3.9
Classifier: Programming Language :: Python :: 3.10
Classifier: Programming Language :: Python :: 3.11
Requires-Python: >=3.6
Requires-Dist: google-generativeai
Requires-Dist: pdfkit
Requires-Dist: markdown2
Requires-Dist: youtube-transcript-api
